sha1prng.py
sha1prng-0.1.0.dist-info/LICENSE
sha1prng-0.1.0.dist-info/METADATA
sha1prng-0.1.0.dist-info/WHEEL
sha1prng-0.1.0.dist-info/top_level.txt
sha1prng-0.1.0.dist-info/RECORD
