Metadata-Version: 2.1
Name: sha1prng
Version: 0.1.0
Summary: SHA1PRNG在Python中的实现，与JAVA SecureRandom的生成结果保持一致。
Author: rRR0VrFP
Maintainer: rRR0VrFP
License: Apache License, Version 2.0
Keywords: sha1prng,hashprng
Classifier: Development Status :: 5 - Production/Stable
Classifier: Intended Audience :: Developers
Classifier: Topic :: Software Development :: Libraries :: Python Modules
Classifier: License :: OSI Approved :: Apache Software License
Classifier: Programming Language :: Python :: 3
Classifier: Programming Language :: Python :: 3 :: Only
License-File: LICENSE
